tabpipe/__init__.py
tabpipe/data_types.py
tabpipe/dataframe/__init__.py
tabpipe/dataframe/dataframe.py
tabpipe/dataframe/pandas.py
tabpipe/dataframe/snowpark.py
tabpipe/exceptions.py
tabpipe/feature.py
tabpipe/pipeline.py
tabpipe/tabpipe.py
tabpipe/transformations/__init__.py
tabpipe/transformations/haversine.py
tabpipe/transformations/list_categorical.py
tabpipe/transformations/passthrough.py
tabpipe/transformations/squared.py
tabpipe/transformations/timestamp_parts.py
tabpipe/transformations/transformation.py
tabpipe/units.py
tabpipe/utils/__init__.py
tabpipe/utils/snowflake.py
tabpipe/utils/strings.py
tabpipe/visualization.py
tabpipe-0.1.1.dist-info/LICENSE
tabpipe-0.1.1.dist-info/METADATA
tabpipe-0.1.1.dist-info/WHEEL
tabpipe-0.1.1.dist-info/RECORD
