Metadata-Version: 2.1
Name: tabpipe
Version: 0.1.1
Summary: A toolkit for tabular data ML preprocessing pipelines.
Home-page: https://github.com/tripadv/tabpipe
License: MIT
Author: José Pinto
Author-email: jopinto@tripadvisor.com
Requires-Python: >=3.9,<3.12
Classifier: Development Status :: 2 - Pre-Alpha
Classifier: Intended Audience :: Developers
Classifier: License :: OSI Approved :: MIT License
Classifier: Natural Language :: English
Classifier: Programming Language :: Python :: 3
Classifier: Programming Language :: Python :: 3.9
Classifier: Programming Language :: Python :: 3.10
Classifier: Programming Language :: Python :: 3.11
Classifier: Programming Language :: Python :: 3.12
Provides-Extra: dev
Provides-Extra: doc
Provides-Extra: test
Requires-Dist: black (>=24.8.0,<25.0.0) ; extra == "test"
Requires-Dist: bump2version (>=1.0.1,<2.0.0) ; extra == "dev"
Requires-Dist: click (<=8.0.2) ; extra == "doc"
Requires-Dist: flake8 (>=7.1.1,<8.0.0) ; extra == "test"
Requires-Dist: flake8-docstrings (>=1.6.0,<2.0.0) ; extra == "test"
Requires-Dist: graphviz (>=0.20.3,<0.21.0) ; extra == "dev"
Requires-Dist: isort (>=5.8.0,<6.0.0) ; extra == "test"
Requires-Dist: jinja2 (<3.1.0) ; extra == "doc"
Requires-Dist: jupyter (>=1.0.0,<2.0.0) ; extra == "dev"
Requires-Dist: mkdocs (>=1.3.0,<2.0.0) ; extra == "doc"
Requires-Dist: mkdocs-autorefs (>=1.0.1,<2.0.0) ; extra == "doc"
Requires-Dist: mkdocs-gen-files (>=0.5.0,<0.6.0) ; extra == "doc"
Requires-Dist: mkdocs-include-markdown-plugin (>=6.2.2,<7.0.0) ; extra == "doc"
Requires-Dist: mkdocs-material (>=9.5.32,<10.0.0) ; extra == "doc"
Requires-Dist: mkdocs-material-extensions (>=1.0.1,<2.0.0)
Requires-Dist: mkdocstrings[python] (>=0.25.2,<0.26.0) ; extra == "doc"
Requires-Dist: mypy (>=1.11.1,<2.0.0) ; extra == "test"
Requires-Dist: numpy (<2)
Requires-Dist: pandas (>=2.2.2,<3.0.0)
Requires-Dist: pip (>=24.2,<25.0) ; extra == "dev"
Requires-Dist: pkginfo (>=1.8.1,<2.0.0)
Requires-Dist: pre-commit (>=3.8.0,<4.0.0) ; extra == "dev"
Requires-Dist: pydantic (>=2.8.2,<3.0.0)
Requires-Dist: pyspark (>=3.5.1,<4.0.0)
Requires-Dist: pytest (>=8.3.2,<9.0.0) ; extra == "test"
Requires-Dist: pytest-cov (>=5.0.0,<6.0.0) ; extra == "test"
Requires-Dist: pytest-dotenv (>=0.5.2,<0.6.0) ; extra == "test"
Requires-Dist: scikit-learn (>=1.5.1,<2.0.0)
Requires-Dist: snowflake-snowpark-python[pandas] (>=1.21.0,<2.0.0)
Requires-Dist: toml (>=0.10.2,<0.11.0) ; extra == "dev"
Requires-Dist: tox (>=4.18.0,<5.0.0) ; extra == "dev"
Requires-Dist: twine (>=5.1.1,<6.0.0) ; extra == "dev"
Requires-Dist: virtualenv (>=20.2.2,<21.0.0) ; extra == "dev"
